QiPy-1.0.5.dist-info/DESCRIPTION.rst
QiPy-1.0.5.dist-info/METADATA
QiPy-1.0.5.dist-info/RECORD
QiPy-1.0.5.dist-info/WHEEL
QiPy-1.0.5.dist-info/metadata.json
QiPy-1.0.5.dist-info/top_level.txt
qipy/__init__.py
qipy/class_group.py
qipy/ideal.py
qipy/quadratic_integer.py
qipy/utilities.py
