Metadata-Version: 2.0
Name: QiPy
Version: 1.0.5
Summary: A Python library to work with elements, ideals, ideal classes and class groups from quadratic integer rings.
Home-page: https://github.com/ranea/QiPy
Author: Adrián Ranea
Author-email: adrianranea@gmail.com
License: MIT
Keywords: quadratic integers ideal class group
Platform: UNKNOWN
Classifier: Development Status :: 5 - Production/Stable
Classifier: Intended Audience :: Education
Classifier: Intended Audience :: Science/Research
Classifier: Topic :: Scientific/Engineering :: Mathematics
Classifier: License :: OSI Approved :: MIT License
Classifier: Programming Language :: Python :: 3
